zope/index/__init__.py
zope/index/interfaces.py
zope/index/nbest.py
zope/index/field/README.rst
zope/index/field/__init__.py
zope/index/field/index.py
zope/index/field/sorting.py
zope/index/field/tests.py
zope/index/keyword/__init__.py
zope/index/keyword/index.py
zope/index/keyword/interfaces.py
zope/index/keyword/tests.py
zope/index/tests/__init__.py
zope/index/tests/test_compile_flags.py
zope/index/tests/tests.py
zope/index/text/README.rst
zope/index/text/__init__.py
zope/index/text/baseindex.py
zope/index/text/cosineindex.py
zope/index/text/htmlsplitter.py
zope/index/text/interfaces.py
zope/index/text/lexicon.py
zope/index/text/okapiindex.py
zope/index/text/okascore.c
zope/index/text/okascore.cp310-win_amd64.pyd
zope/index/text/parsetree.py
zope/index/text/queryparser.py
zope/index/text/ricecode.py
zope/index/text/setops.py
zope/index/text/stopdict.py
zope/index/text/textindex.py
zope/index/text/widcode.py
zope/index/text/tests/__init__.py
zope/index/text/tests/test_baseindex.py
zope/index/text/tests/test_cosineindex.py
zope/index/text/tests/test_htmlsplitter.py
zope/index/text/tests/test_index.py
zope/index/text/tests/test_lexicon.py
zope/index/text/tests/test_okapiindex.py
zope/index/text/tests/test_parsetree.py
zope/index/text/tests/test_queryengine.py
zope/index/text/tests/test_queryparser.py
zope/index/text/tests/test_ricecode.py
zope/index/text/tests/test_setops.py
zope/index/text/tests/test_textindex.py
zope/index/text/tests/test_textindexwrapper.py
zope/index/text/tests/test_widcode.py
zope/index/topic/__init__.py
zope/index/topic/filter.py
zope/index/topic/index.py
zope/index/topic/interfaces.py
zope/index/topic/tests/__init__.py
zope/index/topic/tests/test_filter.py
zope/index/topic/tests/test_index.py
zope_index-8.1.dist-info/licenses/LICENSE.txt
zope_index-8.1.dist-info/METADATA
zope_index-8.1.dist-info/WHEEL
zope_index-8.1.dist-info/top_level.txt
zope_index-8.1.dist-info/RECORD
